contextooor/.DS_Store
contextooor/.env.example
contextooor/.gitignore
contextooor/__init__.py
contextooor/eth_uniswap.py
contextooor/core/addresses.py
contextooor/core/safe_math.py
contextooor/core/V2_router/V2_router.py
contextooor/core/V3_router/V3_router.py
contextooor/core/universal_router/V2_universal_router.py
contextooor/core/universal_router/V3_universal_router.py
contextooor/core/universal_router/data.py
contextooor/core/universal_router/policies.py
contextooor_uniswap-0.0.2.dist-info/WHEEL
contextooor_uniswap-0.0.2.dist-info/METADATA
contextooor_uniswap-0.0.2.dist-info/RECORD
